nyt_archives/__init__.py
nyt_archives/sdk.py
nyt_archives/hooks/__init__.py
nyt_archives/hooks/hook.py
nyt_archives/models/__init__.py
nyt_archives/models/article.py
nyt_archives/models/base.py
nyt_archives/models/byline.py
nyt_archives/models/get_by_year_month_json_ok_response.py
nyt_archives/models/headline.py
nyt_archives/models/keyword.py
nyt_archives/models/multimedia.py
nyt_archives/models/person.py
nyt_archives/models/utils/cast_models.py
nyt_archives/models/utils/json_map.py
nyt_archives/net/__init__.py
nyt_archives/net/environment/__init__.py
nyt_archives/net/environment/environment.py
nyt_archives/net/headers/__init__.py
nyt_archives/net/headers/base_header.py
nyt_archives/net/request_chain/__init__.py
nyt_archives/net/request_chain/request_chain.py
nyt_archives/net/request_chain/handlers/__init__.py
nyt_archives/net/request_chain/handlers/base_handler.py
nyt_archives/net/request_chain/handlers/hook_handler.py
nyt_archives/net/request_chain/handlers/http_handler.py
nyt_archives/net/request_chain/handlers/retry_handler.py
nyt_archives/net/transport/__init__.py
nyt_archives/net/transport/request.py
nyt_archives/net/transport/request_error.py
nyt_archives/net/transport/response.py
nyt_archives/net/transport/serializer.py
nyt_archives/net/transport/utils.py
nyt_archives/services/__init__.py
nyt_archives/services/archive.py
nyt_archives/services/utils/base_service.py
nyt_archives/services/utils/default_headers.py
nyt_archives/services/utils/validator.py
nyt_archives-1.0.0.dist-info/LICENSE
nyt_archives-1.0.0.dist-info/METADATA
nyt_archives-1.0.0.dist-info/WHEEL
nyt_archives-1.0.0.dist-info/top_level.txt
nyt_archives-1.0.0.dist-info/RECORD
