Metadata-Version: 2.1
Name: nyt-archives
Version: 1.0.0
License: MIT
Requires-Python: >=3.7
License-File: LICENSE
Requires-Dist: requests >=2.31.0
